x4util/__about__.py
x4util/conversion/__init__.py
x4util/conversion/x4_dirini.py
x4util/conversion/x4_dirupd.py
x4util/conversion/x4_j4tox4.py
x4util/conversion/x4_maklib.py
x4util/conversion/x4_poipoi.py
x4util/conversion/x4_seqadd.py
x4util/conversion/x4_x4toj4.py
x4util/dict/__init__.py
x4util/dict/x4_dic227.py
x4util/dict/x4_dica2j.py
x4util/dict/x4_dicdis.py
x4util/dict/x4_dicj2a.py
x4util/dict/x4_dicj2t.py
x4util/extract/x4_extmul.py
x4util/extract/x4_makcov.py
x4util/extract/x4_refbib.py
x4util/extract/x4_refdoi.py
x4util/spelling/__init__.py
x4util/spelling/x4_spells.dic
x4util/spelling/x4_spells.py
x4util-0.2.2.dist-info/METADATA
x4util-0.2.2.dist-info/WHEEL
x4util-0.2.2.dist-info/entry_points.txt
x4util-0.2.2.dist-info/licenses/LICENSE
x4util-0.2.2.dist-info/RECORD
