Metadata-Version: 2.4
Name: x4util
Version: 0.2.2
Summary: exfor utility codes
Project-URL: Repository, https://git.oecd-nea.org/exfor/tools/x4util
Project-URL: Issues, https://git.oecd-nea.org/exfor/tools/x4util/-/issues
License-Expression: MIT
License-File: LICENSE
Classifier: Development Status :: 4 - Beta
Classifier: Programming Language :: Python
Classifier: Programming Language :: Python :: 3.8
Classifier: Programming Language :: Python :: 3.9
Classifier: Programming Language :: Python :: 3.10
Classifier: Programming Language :: Python :: 3.11
Classifier: Programming Language :: Python :: 3.12
Requires-Python: >=3.8
Requires-Dist: pylatexenc
Requires-Dist: pyspellchecker
Requires-Dist: requests
